{"storageData": {"batteryCount": 1, "batteries": [{"nameplate": 9800.0, "serialNumber": "R15563P3SSEG12105141018", "modelNumber": "R15563P3SSEG12105141018", "telemetryCount": 289, "telemetries": [{"timeStamp": "2024-08-30 00:01:38", "power": -282.375, "batteryState": 4, "lifeTimeEnergyDischarged": 2655594, "lifeTimeEnergyCharged": 3271983, "batteryPercentageState": 51.99564, "fullPackEnergyAvailable": 9170.0, "internalTemp": 31.6, "ACGridCharging": 0.0}, {"timeStamp": "2024-08-30 00:06:38", "power": -269.5, "batteryState": 4, "lifeTimeEnergyDischarged": 2655614, "lifeTimeEnergyCharged": 3271983, "batteryPercentageState": 51.99564, "fullPackEnergyAvailable": 9170.0, "internalTemp": 31.6, "ACGridCharging": 0.0}, {"timeStamp": "2024-08-30 00:11:38", "power": -286.938, "batteryState": 4, "lifeTimeEnergyDischarged": 2655639, "lifeTimeEnergyCharged": 3271983, "batteryPercentageState": 51.494003, "fullPackEnergyAvailable": 9170.0, "internalTemp": 31.5, "ACGridCharging": 0.0}, {"timeStamp": "2024-08-30 00:16:38", "power": -234.625, "batteryState": 4, "lifeTimeEnergyDischarged": 2655661, "lifeTimeEnergyCharged": 3271983, "batteryPercentageState": 51.494003, "fullPackEnergyAvailable": 9170.0, "internalTemp": 31.5, "ACGridCharging": 0.0}, {"timeStamp": "2024-08-30 00:21:38", "power": -212.187, "batteryState": 4, "lifeTimeEnergyDischarged": 2655680, "lifeTimeEnergyCharged": 3271983, "batteryPercentageState": 50.992367, "fullPackEnergyAvailable": 9170.0, "internalTemp": 31.5, "ACGridCharging": 0.0}, {"timeStamp": "2024-08-30 00:26:38", "power": -230.438, "batteryState": 4, "lifeTimeEnergyDischarged": 2655700, "lifeTimeEnergyCharged": 3271983, "batteryPercentageState": 50.992367, "fullPackEnergyAvailable": 9170.0, "internalTemp": 31.4, "ACGridCharging": 0.0}, {"timeStamp": "2024-08-30 00:31:38", "power": -223.375, "batteryState": 4, "lifeTimeEnergyDischarged": 2655721, "lifeTimeEnergyCharged": 3271983, "batteryPercentageState": 50.49073, "fullPackEnergyAvailable": 9170.0, "internalTemp": 31.4, "ACGridCharging": 0.0}, {"timeStamp": "2024-08-30 00:36:38", "power": -251.125, "batteryState": 4, "lifeTimeEnergyDischarged": 2655741, "lifeTimeEnergyCharged": 3271983, "batteryPercentageState": 50.49073, "fullPackEnergyAvailable": 9170.0, "internalTemp": 31.3, "ACGridCharging": 0.0}, {"timeStamp": "2024-08-30 00:41:38", "power": -184.688, "batteryState": 4, "lifeTimeEnergyDischarged": 2655759, "lifeTimeEnergyCharged": 3271983, "batteryPercentageState": 50.0, "fullPackEnergyAvailable": 9170.0, "internalTemp": 31.3, "ACGridCharging": 0.0}, {"timeStamp": "2024-08-30 00:46:38", "power": -163.562, "batteryState": 4, "lifeTimeEnergyDischarged": 2655775, "lifeTimeEnergyCharged": 3271983, "batteryPercentageState": 50.0, "fullPackEnergyAvailable": 9170.0, "internalTemp": 31.3, "ACGridCharging": 0.0}, {"timeStamp": "2024-08-30 00:51:38", "power": -159.562, "batteryState": 4, "lifeTimeEnergyDischarged": 2655790, "lifeTimeEnergyCharged": 3271983, "batteryPercentageState": 49.498363, "fullPackEnergyAvailable": 9170.0, "internalTemp": 31.2, "ACGridCharging": 0.0}, {"timeStamp": "2024-08-30 00:56:38", "power": -180.562, "batteryState": 4, "lifeTimeEnergyDischarged": 2655808, "lifeTimeEnergyCharged": 3271983, "batteryPercentageState": 49.498363, "fullPackEnergyAvailable": 9170.0, "internalTemp": 31.2, "ACGridCharging": 0.0}, {"timeStamp": "2024-08-30 01:01:38", "power": -204.5, "batteryState": 4, "lifeTimeEnergyDischarged": 2655826, "lifeTimeEnergyCharged": 3271983, "batteryPercentageState": 48.996727, "fullPackEnergyAvailable": 9170.0, "internalTemp": 31.2, "ACGridCharging": 0.0}, {"timeStamp": "2024-08-30 01:06:38", "power": -187.312, "batteryState": 4, "lifeTimeEnergyDischarged": 2655844, "lifeTimeEnergyCharged": 3271983, "batteryPercentageState": 48.996727, "fullPackEnergyAvailable": 9170.0, "internalTemp": 31.1, "ACGridCharging": 0.0}, {"timeStamp": "2024-08-30 01:11:38", "power": -221.125, "batteryState": 4, "lifeTimeEnergyDischarged": 2655863, "lifeTimeEnergyCharged": 3271983, "batteryPercentageState": 45.49618, "fullPackEnergyAvailable": 9170.0, "internalTemp": 31.1, "ACGridCharging": 0.0}, {"timeStamp": "2024-08-30 01:16:38", "power": -225.688, "batteryState": 4, "lifeTimeEnergyDischarged": 2655884, "lifeTimeEnergyCharged": 3271983, "batteryPercentageState": 44.99455, "fullPackEnergyAvailable": 9170.0, "internalTemp": 31.0, "ACGridCharging": 0.0}, {"timeStamp": "2024-08-30 01:21:38", "power": -213.188, "batteryState": 4, "lifeTimeEnergyDischarged": 2655904, "lifeTimeEnergyCharged": 3271983, "batteryPercentageState": 44.99455, "fullPackEnergyAvailable": 9170.0, "internalTemp": 31.0, "ACGridCharging": 0.0}, {"timeStamp": "2024-08-30 01:26:38", "power": -270.562, "batteryState": 4, "lifeTimeEnergyDischarged": 2655925, "lifeTimeEnergyCharged": 3271983, "batteryPercentageState": 44.99455, "fullPackEnergyAvailable": 9170.0, "internalTemp": 31.0, "ACGridCharging": 0.0}, {"timeStamp": "2024-08-30 01:31:38", "power": -221.563, "batteryState": 4, "lifeTimeEnergyDischarged": 2655948, "lifeTimeEnergyCharged": 3271983, "batteryPercentageState": 44.492912, "fullPackEnergyAvailable": 9170.0, "internalTemp": 30.9, "ACGridCharging": 0.0}, {"timeStamp": "2024-08-30 01:36:38", "power": -211.688, "batteryState": 4, "lifeTimeEnergyDischarged": 2655968, "lifeTimeEnergyCharged": 3271983, "batteryPercentageState": 44.492912, "fullPackEnergyAvailable": 9170.0, "internalTemp": 30.9, "ACGridCharging": 0.0}, {"timeStamp": "2024-08-30 01:41:38", "power": -205.625, "batteryState": 4, "lifeTimeEnergyDischarged": 2655988, "lifeTimeEnergyCharged": 3271983, "batteryPercentageState": 43.991276, "fullPackEnergyAvailable": 9170.0, "internalTemp": 30.9, "ACGridCharging": 0.0}, {"timeStamp": "2024-08-30 01:46:38", "power": -199.0, "batteryState": 4, "lifeTimeEnergyDischarged": 2656007, "lifeTimeEnergyCharged": 3271983, "batteryPercentageState": 43.991276, "fullPackEnergyAvailable": 9170.0, "internalTemp": 30.8, "ACGridCharging": 0.0}, {"timeStamp": "2024-08-30 01:51:38", "power": -326.5, "batteryState": 4, "lifeTimeEnergyDischarged": 2656027, "lifeTimeEnergyCharged": 3271983, "batteryPercentageState": 43.991276, "fullPackEnergyAvailable": 9170.0, "internalTemp": 30.8, "ACGridCharging": 0.0}, {"timeStamp": "2024-08-30 01:56:38", "power": -188.062, "batteryState": 4, "lifeTimeEnergyDischarged": 2656056, "lifeTimeEnergyCharged": 3271983, "batteryPercentageState": 43.48964, "fullPackEnergyAvailable": 9170.0, "internalTemp": 30.7, "ACGridCharging": 0.0}, {"timeStamp": "2024-08-30 02:01:38", "power": -206.75, "batteryState": 4, "lifeTimeEnergyDischarged": 2656072, "lifeTimeEnergyCharged": 3271983, "batteryPercentageState": 43.48964, "fullPackEnergyAvailable": 9170.0, "internalTemp": 30.7, "ACGridCharging": 0.0}, {"timeStamp": "2024-08-30 02:06:38", "power": -170.438, "batteryState": 4, "lifeTimeEnergyDischarged": 2656088, "lifeTimeEnergyCharged": 3271983, "batteryPercentageState": 43.48964, "fullPackEnergyAvailable": 9170.0, "internalTemp": 30.7, "ACGridCharging": 0.0}, {"timeStamp": "2024-08-30 02:11:38", "power": -155.938, "batteryState": 4, "lifeTimeEnergyDischarged": 2656103, "lifeTimeEnergyCharged": 3271983, "batteryPercentageState": 43.48964, "fullPackEnergyAvailable": 9170.0, "internalTemp": 30.6, "ACGridCharging": 0.0}, {"timeStamp": "2024-08-30 02:16:38", "power": -180.5, "batteryState": 4, "lifeTimeEnergyDischarged": 2656119, "lifeTimeEnergyCharged": 3271983, "batteryPercentageState": 42.99891, "fullPackEnergyAvailable": 9170.0, "internalTemp": 30.6, "ACGridCharging": 0.0}, {"timeStamp": "2024-08-30 02:21:38", "power": -227.875, "batteryState": 4, "lifeTimeEnergyDischarged": 2656139, "lifeTimeEnergyCharged": 3271983, "batteryPercentageState": 42.99891, "fullPackEnergyAvailable": 9170.0, "internalTemp": 30.6, "ACGridCharging": 0.0}, {"timeStamp": "2024-08-30 02:26:38", "power": -124.188, "batteryState": 4, "lifeTimeEnergyDischarged": 2656151, "lifeTimeEnergyCharged": 3271983, "batteryPercentageState": 42.99891, "fullPackEnergyAvailable": 9170.0, "internalTemp": 30.5, "ACGridCharging": 0.0}, {"timeStamp": "2024-08-30 02:31:38", "power": -166.0, "batteryState": 4, "lifeTimeEnergyDischarged": 2656165, "lifeTimeEnergyCharged": 3271983, "batteryPercentageState": 42.99891, "fullPackEnergyAvailable": 9170.0, "internalTemp": 30.5, "ACGridCharging": 0.0}, {"timeStamp": "2024-08-30 02:36:38", "power": -160.125, "batteryState": 4, "lifeTimeEnergyDischarged": 2656182, "lifeTimeEnergyCharged": 3271983, "batteryPercentageState": 42.497272, "fullPackEnergyAvailable": 9170.0, "internalTemp": 30.5, "ACGridCharging": 0.0}, {"timeStamp": "2024-08-30 02:41:38", "power": -188.625, "batteryState": 4, "lifeTimeEnergyDischarged": 2656201, "lifeTimeEnergyCharged": 3271983, "batteryPercentageState": 42.497272, "fullPackEnergyAvailable": 9170.0, "internalTemp": 30.4, "ACGridCharging": 0.0}, {"timeStamp": "2024-08-30 02:46:38", "power": -263.875, "batteryState": 4, "lifeTimeEnergyDischarged": 2656223, "lifeTimeEnergyCharged": 3271983, "batteryPercentageState": 41.99564, "fullPackEnergyAvailable": 9170.0, "internalTemp": 30.4, "ACGridCharging": 0.0}, {"timeStamp": "2024-08-30 02:51:38", "power": -185.375, "batteryState": 4, "lifeTimeEnergyDischarged": 2656242, "lifeTimeEnergyCharged": 3271983, "batteryPercentageState": 41.99564, "fullPackEnergyAvailable": 9170.0, "internalTemp": 30.4, "ACGridCharging": 0.0}, {"timeStamp": "2024-08-30 02:56:38", "power": -165.438, "batteryState": 4, "lifeTimeEnergyDischarged": 2656264, "lifeTimeEnergyCharged": 3271983, "batteryPercentageState": 40.0, "fullPackEnergyAvailable": 9170.0, "internalTemp": 30.3, "ACGridCharging": 0.0}, {"timeStamp": "2024-08-30 03:01:38", "power": -222.562, "batteryState": 4, "lifeTimeEnergyDischarged": 2656283, "lifeTimeEnergyCharged": 3271983, "batteryPercentageState": 40.0, "fullPackEnergyAvailable": 9170.0, "internalTemp": 30.3, "ACGridCharging": 0.0}, {"timeStamp": "2024-08-30 03:06:38", "power": -186.188, "batteryState": 4, "lifeTimeEnergyDischarged": 2656301, "lifeTimeEnergyCharged": 3271983, "batteryPercentageState": 39.498363, "fullPackEnergyAvailable": 9170.0, "internalTemp": 30.3, "ACGridCharging": 0.0}, {"timeStamp": "2024-08-30 03:11:38", "power": -205.938, "batteryState": 4, "lifeTimeEnergyDischarged": 2656321, "lifeTimeEnergyCharged": 3271983, "batteryPercentageState": 39.498363, "fullPackEnergyAvailable": 9170.0, "internalTemp": 30.2, "ACGridCharging": 0.0}, {"timeStamp": "2024-08-30 03:16:38", "power": -186.0, "batteryState": 4, "lifeTimeEnergyDischarged": 2656341, "lifeTimeEnergyCharged": 3271983, "batteryPercentageState": 39.498363, "fullPackEnergyAvailable": 9170.0, "internalTemp": 30.2, "ACGridCharging": 0.0}, {"timeStamp": "2024-08-30 03:21:38", "power": -172.312, "batteryState": 4, "lifeTimeEnergyDischarged": 2656359, "lifeTimeEnergyCharged": 3271983, "batteryPercentageState": 38.996727, "fullPackEnergyAvailable": 9170.0, "internalTemp": 30.2, "ACGridCharging": 0.0}, {"timeStamp": "2024-08-30 03:26:38", "power": -190.875, "batteryState": 4, "lifeTimeEnergyDischarged": 2656377, "lifeTimeEnergyCharged": 3271983, "batteryPercentageState": 38.996727, "fullPackEnergyAvailable": 9170.0, "internalTemp": 30.1, "ACGridCharging": 0.0}, {"timeStamp": "2024-08-30 03:31:38", "power": -179.688, "batteryState": 4, "lifeTimeEnergyDischarged": 2656395, "lifeTimeEnergyCharged": 3271983, "batteryPercentageState": 38.996727, "fullPackEnergyAvailable": 9170.0, "internalTemp": 30.1, "ACGridCharging": 0.0}, {"timeStamp": "2024-08-30 03:36:38", "power": -256.75, "batteryState": 4, "lifeTimeEnergyDischarged": 2656414, "lifeTimeEnergyCharged": 3271983, "batteryPercentageState": 38.495094, "fullPackEnergyAvailable": 9170.0, "internalTemp": 30.1, "ACGridCharging": 0.0}, {"timeStamp": "2024-08-30 03:41:38", "power": -188.562, "batteryState": 4, "lifeTimeEnergyDischarged": 2656433, "lifeTimeEnergyCharged": 3271983, "batteryPercentageState": 38.495094, "fullPackEnergyAvailable": 9170.0, "internalTemp": 30.1, "ACGridCharging": 0.0}, {"timeStamp": "2024-08-30 03:46:38", "power": -162.25, "batteryState": 4, "lifeTimeEnergyDischarged": 2656449, "lifeTimeEnergyCharged": 3271983, "batteryPercentageState": 38.495094, "fullPackEnergyAvailable": 9170.0, "internalTemp": 30.0, "ACGridCharging": 0.0}, {"timeStamp": "2024-08-30 03:51:38", "power": -164.5, "batteryState": 4, "lifeTimeEnergyDischarged": 2656464, "lifeTimeEnergyCharged": 3271983, "batteryPercentageState": 38.495094, "fullPackEnergyAvailable": 9170.0, "internalTemp": 30.0, "ACGridCharging": 0.0}, {"timeStamp": "2024-08-30 03:56:38", "power": -177.062, "batteryState": 4, "lifeTimeEnergyDischarged": 2656482, "lifeTimeEnergyCharged": 3271983, "batteryPercentageState": 37.993458, "fullPackEnergyAvailable": 9170.0, "internalTemp": 30.0, "ACGridCharging": 0.0}, {"timeStamp": "2024-08-30 04:01:38", "power": -166.438, "batteryState": 4, "lifeTimeEnergyDischarged": 2656497, "lifeTimeEnergyCharged": 3271983, "batteryPercentageState": 37.993458, "fullPackEnergyAvailable": 9170.0, "internalTemp": 29.9, "ACGridCharging": 0.0}, {"timeStamp": "2024-08-30 04:06:38", "power": -135.188, "batteryState": 4, "lifeTimeEnergyDischarged": 2656517, "lifeTimeEnergyCharged": 3271983, "batteryPercentageState": 37.993458, "fullPackEnergyAvailable": 9170.0, "internalTemp": 29.9, "ACGridCharging": 0.0}, {"timeStamp": "2024-08-30 04:11:38", "power": -221.25, "batteryState": 4, "lifeTimeEnergyDischarged": 2656533, "lifeTimeEnergyCharged": 3271983, "batteryPercentageState": 35.997818, "fullPackEnergyAvailable": 9170.0, "internalTemp": 29.9, "ACGridCharging": 0.0}, {"timeStamp": "2024-08-30 04:16:38", "power": -181.75, "batteryState": 4, "lifeTimeEnergyDischarged": 2656549, "lifeTimeEnergyCharged": 3271983, "batteryPercentageState": 35.49618, "fullPackEnergyAvailable": 9170.0, "internalTemp": 29.9, "ACGridCharging": 0.0}, {"timeStamp": "2024-08-30 04:21:38", "power": -199.562, "batteryState": 4, "lifeTimeEnergyDischarged": 2656565, "lifeTimeEnergyCharged": 3271983, "batteryPercentageState": 35.49618, "fullPackEnergyAvailable": 9170.0, "internalTemp": 29.9, "ACGridCharging": 0.0}, {"timeStamp": "2024-08-30 04:26:38", "power": -219.25, "batteryState": 4, "lifeTimeEnergyDischarged": 2656584, "lifeTimeEnergyCharged": 3271983, "batteryPercentageState": 35.49618, "fullPackEnergyAvailable": 9170.0, "internalTemp": 29.8, "ACGridCharging": 0.0}, {"timeStamp": "2024-08-30 04:31:38", "power": -264.5, "batteryState": 4, "lifeTimeEnergyDischarged": 2656609, "lifeTimeEnergyCharged": 3271983, "batteryPercentageState": 34.99455, "fullPackEnergyAvailable": 9170.0, "internalTemp": 29.8, "ACGridCharging": 0.0}, {"timeStamp": "2024-08-30 04:36:38", "power": -184.875, "batteryState": 4, "lifeTimeEnergyDischarged": 2656628, "lifeTimeEnergyCharged": 3271983, "batteryPercentageState": 34.99455, "fullPackEnergyAvailable": 9170.0, "internalTemp": 29.8, "ACGridCharging": 0.0}, {"timeStamp": "2024-08-30 04:41:38", "power": -203.062, "batteryState": 4, "lifeTimeEnergyDischarged": 2656647, "lifeTimeEnergyCharged": 3271983, "batteryPercentageState": 34.99455, "fullPackEnergyAvailable": 9170.0, "internalTemp": 29.8, "ACGridCharging": 0.0}, {"timeStamp": "2024-08-30 04:46:38", "power": -222.25, "batteryState": 4, "lifeTimeEnergyDischarged": 2656666, "lifeTimeEnergyCharged": 3271983, "batteryPercentageState": 34.492912, "fullPackEnergyAvailable": 9170.0, "internalTemp": 29.8, "ACGridCharging": 0.0}, {"timeStamp": "2024-08-30 04:51:38", "power": -194.562, "batteryState": 4, "lifeTimeEnergyDischarged": 2656685, "lifeTimeEnergyCharged": 3271983, "batteryPercentageState": 34.492912, "fullPackEnergyAvailable": 9170.0, "internalTemp": 29.7, "ACGridCharging": 0.0}, {"timeStamp": "2024-08-30 04:56:38", "power": -245.188, "batteryState": 4, "lifeTimeEnergyDischarged": 2656711, "lifeTimeEnergyCharged": 3271983, "batteryPercentageState": 33.991276, "fullPackEnergyAvailable": 9170.0, "internalTemp": 29.7, "ACGridCharging": 0.0}, {"timeStamp": "2024-08-30 05:01:38", "power": -158.562, "batteryState": 4, "lifeTimeEnergyDischarged": 2656728, "lifeTimeEnergyCharged": 3271983, "batteryPercentageState": 33.991276, "fullPackEnergyAvailable": 9170.0, "internalTemp": 29.7, "ACGridCharging": 0.0}, {"timeStamp": "2024-08-30 05:06:38", "power": -164.312, "batteryState": 4, "lifeTimeEnergyDischarged": 2656743, "lifeTimeEnergyCharged": 3271983, "batteryPercentageState": 33.991276, "fullPackEnergyAvailable": 9170.0, "internalTemp": 29.7, "ACGridCharging": 0.0}, {"timeStamp": "2024-08-30 05:11:38", "power": -150.5, "batteryState": 4, "lifeTimeEnergyDischarged": 2656757, "lifeTimeEnergyCharged": 3271983, "batteryPercentageState": 33.991276, "fullPackEnergyAvailable": 9170.0, "internalTemp": 29.7, "ACGridCharging": 0.0}, {"timeStamp": "2024-08-30 05:16:38", "power": -154.625, "batteryState": 4, "lifeTimeEnergyDischarged": 2656772, "lifeTimeEnergyCharged": 3271983, "batteryPercentageState": 33.991276, "fullPackEnergyAvailable": 9170.0, "internalTemp": 29.6, "ACGridCharging": 0.0}, {"timeStamp": "2024-08-30 05:21:38", "power": -121.625, "batteryState": 4, "lifeTimeEnergyDischarged": 2656784, "lifeTimeEnergyCharged": 3271983, "batteryPercentageState": 33.48964, "fullPackEnergyAvailable": 9170.0, "internalTemp": 29.6, "ACGridCharging": 0.0}, {"timeStamp": "2024-08-30 05:26:38", "power": -176.125, "batteryState": 4, "lifeTimeEnergyDischarged": 2656797, "lifeTimeEnergyCharged": 3271983, "batteryPercentageState": 33.48964, "fullPackEnergyAvailable": 9170.0, "internalTemp": 29.6, "ACGridCharging": 0.0}, {"timeStamp": "2024-08-30 05:31:38", "power": -200.188, "batteryState": 4, "lifeTimeEnergyDischarged": 2656814, "lifeTimeEnergyCharged": 3271983, "batteryPercentageState": 33.48964, "fullPackEnergyAvailable": 9170.0, "internalTemp": 29.6, "ACGridCharging": 0.0}, {"timeStamp": "2024-08-30 05:36:38", "power": -190.812, "batteryState": 4, "lifeTimeEnergyDischarged": 2656852, "lifeTimeEnergyCharged": 3271983, "batteryPercentageState": 32.99891, "fullPackEnergyAvailable": 9170.0, "internalTemp": 29.6, "ACGridCharging": 0.0}, {"timeStamp": "2024-08-30 05:41:38", "power": -220.875, "batteryState": 4, "lifeTimeEnergyDischarged": 2656870, "lifeTimeEnergyCharged": 3271983, "batteryPercentageState": 32.99891, "fullPackEnergyAvailable": 9170.0, "internalTemp": 29.6, "ACGridCharging": 0.0}, {"timeStamp": "2024-08-30 05:46:38", "power": -201.75, "batteryState": 4, "lifeTimeEnergyDischarged": 2656888, "lifeTimeEnergyCharged": 3271983, "batteryPercentageState": 32.497272, "fullPackEnergyAvailable": 9170.0, "internalTemp": 29.6, "ACGridCharging": 0.0}, {"timeStamp": "2024-08-30 05:51:38", "power": -147.875, "batteryState": 4, "lifeTimeEnergyDischarged": 2656906, "lifeTimeEnergyCharged": 3271983, "batteryPercentageState": 32.497272, "fullPackEnergyAvailable": 9170.0, "internalTemp": 29.6, "ACGridCharging": 0.0}, {"timeStamp": "2024-08-30 05:56:38", "power": -194.188, "batteryState": 4, "lifeTimeEnergyDischarged": 2656927, "lifeTimeEnergyCharged": 3271983, "batteryPercentageState": 31.995638, "fullPackEnergyAvailable": 9170.0, "internalTemp": 29.6, "ACGridCharging": 0.0}, {"timeStamp": "2024-08-30 06:01:38", "power": -187.375, "batteryState": 4, "lifeTimeEnergyDischarged": 2656945, "lifeTimeEnergyCharged": 3271983, "batteryPercentageState": 31.995638, "fullPackEnergyAvailable": 9170.0, "internalTemp": 29.6, "ACGridCharging": 0.0}, {"timeStamp": "2024-08-30 06:06:38", "power": -178.188, "batteryState": 4, "lifeTimeEnergyDischarged": 2656963, "lifeTimeEnergyCharged": 3271983, "batteryPercentageState": 31.995638, "fullPackEnergyAvailable": 9170.0, "internalTemp": 29.6, "ACGridCharging": 0.0}, {"timeStamp": "2024-08-30 06:11:38", "power": -163.25, "batteryState": 4, "lifeTimeEnergyDischarged": 2656976, "lifeTimeEnergyCharged": 3271983, "batteryPercentageState": 31.494001, "fullPackEnergyAvailable": 9170.0, "internalTemp": 29.6, "ACGridCharging": 0.0}, {"timeStamp": "2024-08-30 06:16:38", "power": -140.125, "batteryState": 4, "lifeTimeEnergyDischarged": 2656988, "lifeTimeEnergyCharged": 3271983, "batteryPercentageState": 31.494001, "fullPackEnergyAvailable": 9170.0, "internalTemp": 29.6, "ACGridCharging": 0.0}, {"timeStamp": "2024-08-30 06:21:38", "power": -77.5625, "batteryState": 4, "lifeTimeEnergyDischarged": 2657002, "lifeTimeEnergyCharged": 3271983, "batteryPercentageState": 30.992367, "fullPackEnergyAvailable": 9170.0, "internalTemp": 29.6, "ACGridCharging": 0.0}, {"timeStamp": "2024-08-30 06:26:38", "power": -93.125, "batteryState": 4, "lifeTimeEnergyDischarged": 2657015, "lifeTimeEnergyCharged": 3271983, "batteryPercentageState": 30.992367, "fullPackEnergyAvailable": 9170.0, "internalTemp": 29.6, "ACGridCharging": 0.0}, {"timeStamp": "2024-08-30 06:31:38", "power": -160.625, "batteryState": 4, "lifeTimeEnergyDischarged": 2657029, "lifeTimeEnergyCharged": 3271983, "batteryPercentageState": 30.992367, "fullPackEnergyAvailable": 9170.0, "internalTemp": 29.6, "ACGridCharging": 0.0}, {"timeStamp": "2024-08-30 06:36:38", "power": -216.062, "batteryState": 4, "lifeTimeEnergyDischarged": 2657044, "lifeTimeEnergyCharged": 3271983, "batteryPercentageState": 30.49073, "fullPackEnergyAvailable": 9170.0, "internalTemp": 29.6, "ACGridCharging": 0.0}, {"timeStamp": "2024-08-30 06:41:38", "power": -160.062, "batteryState": 4, "lifeTimeEnergyDischarged": 2657062, "lifeTimeEnergyCharged": 3271983, "batteryPercentageState": 30.49073, "fullPackEnergyAvailable": 9170.0, "internalTemp": 29.6, "ACGridCharging": 0.0}, {"timeStamp": "2024-08-30 06:46:38", "power": -246.0, "batteryState": 4, "lifeTimeEnergyDischarged": 2657077, "lifeTimeEnergyCharged": 3271983, "batteryPercentageState": 30.0, "fullPackEnergyAvailable": 9170.0, "internalTemp": 29.6, "ACGridCharging": 0.0}, {"timeStamp": "2024-08-30 06:51:38", "power": -176.875, "batteryState": 4, "lifeTimeEnergyDischarged": 2657096, "lifeTimeEnergyCharged": 3271983, "batteryPercentageState": 30.0, "fullPackEnergyAvailable": 9170.0, "internalTemp": 29.6, "ACGridCharging": 0.0}, {"timeStamp": "2024-08-30 06:56:38", "power": -90.0, "batteryState": 4, "lifeTimeEnergyDischarged": 2657112, "lifeTimeEnergyCharged": 3271983, "batteryPercentageState": 29.498363, "fullPackEnergyAvailable": 9170.0, "internalTemp": 29.6, "ACGridCharging": 0.0}, {"timeStamp": "2024-08-30 07:01:38", "power": -219.375, "batteryState": 4, "lifeTimeEnergyDischarged": 2657127, "lifeTimeEnergyCharged": 3271983, "batteryPercentageState": 29.498363, "fullPackEnergyAvailable": 9170.0, "internalTemp": 29.6, "ACGridCharging": 0.0}, {"timeStamp": "2024-08-30 07:06:38", "power": -158.25, "batteryState": 4, "lifeTimeEnergyDischarged": 2657144, "lifeTimeEnergyCharged": 3271983, "batteryPercentageState": 28.996729, "fullPackEnergyAvailable": 9170.0, "internalTemp": 29.6, "ACGridCharging": 0.0}, {"timeStamp": "2024-08-30 07:11:38", "power": -154.625, "batteryState": 4, "lifeTimeEnergyDischarged": 2657158, "lifeTimeEnergyCharged": 3271983, "batteryPercentageState": 28.996729, "fullPackEnergyAvailable": 9170.0, "internalTemp": 29.6, "ACGridCharging": 0.0}, {"timeStamp": "2024-08-30 07:16:38", "power": -158.938, "batteryState": 4, "lifeTimeEnergyDischarged": 2657170, "lifeTimeEnergyCharged": 3271983, "batteryPercentageState": 28.495092, "fullPackEnergyAvailable": 9170.0, "internalTemp": 29.6, "ACGridCharging": 0.0}, {"timeStamp": "2024-08-30 07:21:38", "power": -121.125, "batteryState": 4, "lifeTimeEnergyDischarged": 2657181, "lifeTimeEnergyCharged": 3271983, "batteryPercentageState": 24.492912, "fullPackEnergyAvailable": 9170.0, "internalTemp": 29.6, "ACGridCharging": 0.0}, {"timeStamp": "2024-08-30 07:26:38", "power": -161.688, "batteryState": 4, "lifeTimeEnergyDischarged": 2657195, "lifeTimeEnergyCharged": 3271983, "batteryPercentageState": 24.492912, "fullPackEnergyAvailable": 9170.0, "internalTemp": 29.6, "ACGridCharging": 0.0}, {"timeStamp": "2024-08-30 07:31:38", "power": -83.5625, "batteryState": 4, "lifeTimeEnergyDischarged": 2657205, "lifeTimeEnergyCharged": 3271983, "batteryPercentageState": 24.492912, "fullPackEnergyAvailable": 9170.0, "internalTemp": 29.6, "ACGridCharging": 0.0}, {"timeStamp": "2024-08-30 07:36:38", "power": -75.6875, "batteryState": 4, "lifeTimeEnergyDischarged": 2657212, "lifeTimeEnergyCharged": 3271983, "batteryPercentageState": 24.492912, "fullPackEnergyAvailable": 9170.0, "internalTemp": 29.6, "ACGridCharging": 0.0}, {"timeStamp": "2024-08-30 07:41:38", "power": 0.0, "batteryState": 6, "lifeTimeEnergyDischarged": 2657218, "lifeTimeEnergyCharged": 3271983, "batteryPercentageState": 24.492912, "fullPackEnergyAvailable": 9170.0, "internalTemp": 29.6, "ACGridCharging": 0.0}, {"timeStamp": "2024-08-30 07:46:38", "power": 0.0, "batteryState": 6, "lifeTimeEnergyDischarged": 2657224, "lifeTimeEnergyCharged": 3271983, "batteryPercentageState": 24.492912, "fullPackEnergyAvailable": 9170.0, "internalTemp": 29.6, "ACGridCharging": 0.0}, {"timeStamp": "2024-08-30 07:51:38", "power": -116.75, "batteryState": 4, "lifeTimeEnergyDischarged": 2657234, "lifeTimeEnergyCharged": 3271983, "batteryPercentageState": 23.991276, "fullPackEnergyAvailable": 9170.0, "internalTemp": 29.6, "ACGridCharging": 0.0}, {"timeStamp": "2024-08-30 07:56:38", "power": 0.0, "batteryState": 6, "lifeTimeEnergyDischarged": 2657240, "lifeTimeEnergyCharged": 3271983, "batteryPercentageState": 23.991276, "fullPackEnergyAvailable": 9170.0, "internalTemp": 29.6, "ACGridCharging": 0.0}, {"timeStamp": "2024-08-30 08:01:38", "power": 0.0, "batteryState": 6, "lifeTimeEnergyDischarged": 2657241, "lifeTimeEnergyCharged": 3271983, "batteryPercentageState": 23.991276, "fullPackEnergyAvailable": 9170.0, "internalTemp": 29.6, "ACGridCharging": 0.0}, {"timeStamp": "2024-08-30 08:06:38", "power": 0.0, "batteryState": 6, "lifeTimeEnergyDischarged": 2657242, "lifeTimeEnergyCharged": 3271983, "batteryPercentageState": 23.991276, "fullPackEnergyAvailable": 9170.0, "internalTemp": 29.6, "ACGridCharging": 0.0}, {"timeStamp": "2024-08-30 08:11:38", "power": 0.0, "batteryState": 6, "lifeTimeEnergyDischarged": 2657242, "lifeTimeEnergyCharged": 3271983, "batteryPercentageState": 23.991276, "fullPackEnergyAvailable": 9170.0, "internalTemp": 29.5, "ACGridCharging": 0.0}, {"timeStamp": "2024-08-30 08:16:38", "power": 0.0, "batteryState": 6, "lifeTimeEnergyDischarged": 2657242, "lifeTimeEnergyCharged": 3271983, "batteryPercentageState": 23.991276, "fullPackEnergyAvailable": 9170.0, "internalTemp": 29.5, "ACGridCharging": 0.0}, {"timeStamp": "2024-08-30 08:21:38", "power": 0.0, "batteryState": 6, "lifeTimeEnergyDischarged": 2657242, "lifeTimeEnergyCharged": 3271983, "batteryPercentageState": 23.991276, "fullPackEnergyAvailable": 9170.0, "internalTemp": 29.5, "ACGridCharging": 0.0}, {"timeStamp": "2024-08-30 08:26:38", "power": 0.0, "batteryState": 6, "lifeTimeEnergyDischarged": 2657242, "lifeTimeEnergyCharged": 3271983, "batteryPercentageState": 23.991276, "fullPackEnergyAvailable": 9170.0, "internalTemp": 29.5, "ACGridCharging": 0.0}, {"timeStamp": "2024-08-30 08:31:38", "power": 0.0, "batteryState": 1, "lifeTimeEnergyDischarged": 2657242, "lifeTimeEnergyCharged": 3271985, "batteryPercentageState": 23.991276, "fullPackEnergyAvailable": 9170.0, "internalTemp": 29.5, "ACGridCharging": 0.0}, {"timeStamp": "2024-08-30 08:36:38", "power": 198.25, "batteryState": 3, "lifeTimeEnergyDischarged": 2657242, "lifeTimeEnergyCharged": 3271994, "batteryPercentageState": 23.991276, "fullPackEnergyAvailable": 9170.0, "internalTemp": 29.5, "ACGridCharging": 0.0}, {"timeStamp": "2024-08-30 08:41:38", "power": -29.5625, "batteryState": 1, "lifeTimeEnergyDischarged": 2657242, "lifeTimeEnergyCharged": 3272009, "batteryPercentageState": 23.991276, "fullPackEnergyAvailable": 9170.0, "internalTemp": 29.4, "ACGridCharging": 0.0}, {"timeStamp": "2024-08-30 08:46:38", "power": 1044.44, "batteryState": 3, "lifeTimeEnergyDischarged": 2657242, "lifeTimeEnergyCharged": 3272022, "batteryPercentageState": 24.492912, "fullPackEnergyAvailable": 9170.0, "internalTemp": 29.4, "ACGridCharging": 0.0}, {"timeStamp": "2024-08-30 08:51:38", "power": 1097.62, "batteryState": 3, "lifeTimeEnergyDischarged": 2657242, "lifeTimeEnergyCharged": 3272042, "batteryPercentageState": 24.492912, "fullPackEnergyAvailable": 9170.0, "internalTemp": 29.4, "ACGridCharging": 0.0}, {"timeStamp": "2024-08-30 08:56:38", "power": 87.5625, "batteryState": 3, "lifeTimeEnergyDischarged": 2657242, "lifeTimeEnergyCharged": 3272070, "batteryPercentageState": 24.994547, "fullPackEnergyAvailable": 9170.0, "internalTemp": 29.4, "ACGridCharging": 0.0}, {"timeStamp": "2024-08-30 09:01:38", "power": 794.125, "batteryState": 3, "lifeTimeEnergyDischarged": 2657255, "lifeTimeEnergyCharged": 3272118, "batteryPercentageState": 25.496183, "fullPackEnergyAvailable": 9170.0, "internalTemp": 29.3, "ACGridCharging": 0.0}, {"timeStamp": "2024-08-30 09:06:38", "power": 36.625, "batteryState": 1, "lifeTimeEnergyDischarged": 2657258, "lifeTimeEnergyCharged": 3272185, "batteryPercentageState": 25.99782, "fullPackEnergyAvailable": 9170.0, "internalTemp": 29.3, "ACGridCharging": 0.0}, {"timeStamp": "2024-08-30 09:11:38", "power": 1283.5, "batteryState": 3, "lifeTimeEnergyDischarged": 2657259, "lifeTimeEnergyCharged": 3272248, "batteryPercentageState": 26.990185, "fullPackEnergyAvailable": 9170.0, "internalTemp": 29.3, "ACGridCharging": 0.0}, {"timeStamp": "2024-08-30 09:16:38", "power": 997.75, "batteryState": 3, "lifeTimeEnergyDischarged": 2657259, "lifeTimeEnergyCharged": 3272327, "batteryPercentageState": 27.993458, "fullPackEnergyAvailable": 9170.0, "internalTemp": 29.3, "ACGridCharging": 0.0}, {"timeStamp": "2024-08-30 09:21:38", "power": 1045.94, "batteryState": 3, "lifeTimeEnergyDischarged": 2657259, "lifeTimeEnergyCharged": 3272421, "batteryPercentageState": 28.996729, "fullPackEnergyAvailable": 9170.0, "internalTemp": 29.2, "ACGridCharging": 0.0}, {"timeStamp": "2024-08-30 09:26:38", "power": 1112.88, "batteryState": 3, "lifeTimeEnergyDischarged": 2657259, "lifeTimeEnergyCharged": 3272521, "batteryPercentageState": 30.0, "fullPackEnergyAvailable": 9170.0, "internalTemp": 29.2, "ACGridCharging": 0.0}, {"timeStamp": "2024-08-30 09:31:38", "power": 1162.25, "batteryState": 3, "lifeTimeEnergyDischarged": 2657259, "lifeTimeEnergyCharged": 3272626, "batteryPercentageState": 30.992367, "fullPackEnergyAvailable": 9170.0, "internalTemp": 29.2, "ACGridCharging": 0.0}, {"timeStamp": "2024-08-30 09:36:38", "power": 1094.06, "batteryState": 3, "lifeTimeEnergyDischarged": 2657259, "lifeTimeEnergyCharged": 3272733, "batteryPercentageState": 31.995638, "fullPackEnergyAvailable": 9170.0, "internalTemp": 29.2, "ACGridCharging": 0.0}, {"timeStamp": "2024-08-30 09:41:38", "power": 1260.06, "batteryState": 3, "lifeTimeEnergyDischarged": 2657259, "lifeTimeEnergyCharged": 3272843, "batteryPercentageState": 33.48964, "fullPackEnergyAvailable": 9170.0, "internalTemp": 29.2, "ACGridCharging": 0.0}, {"timeStamp": "2024-08-30 09:46:38", "power": 1309.81, "batteryState": 3, "lifeTimeEnergyDischarged": 2657259, "lifeTimeEnergyCharged": 3272962, "batteryPercentageState": 34.492912, "fullPackEnergyAvailable": 9170.0, "internalTemp": 29.3, "ACGridCharging": 0.0}, {"timeStamp": "2024-08-30 09:51:38", "power": 1360.94, "batteryState": 3, "lifeTimeEnergyDischarged": 2657259, "lifeTimeEnergyCharged": 3273085, "batteryPercentageState": 35.997818, "fullPackEnergyAvailable": 9170.0, "internalTemp": 29.4, "ACGridCharging": 0.0}, {"timeStamp": "2024-08-30 09:56:38", "power": 1425.31, "batteryState": 3, "lifeTimeEnergyDischarged": 2657259, "lifeTimeEnergyCharged": 3273211, "batteryPercentageState": 37.49182, "fullPackEnergyAvailable": 9170.0, "internalTemp": 29.5, "ACGridCharging": 0.0}, {"timeStamp": "2024-08-30 10:01:38", "power": 1474.31, "batteryState": 3, "lifeTimeEnergyDischarged": 2657259, "lifeTimeEnergyCharged": 3273346, "batteryPercentageState": 38.495094, "fullPackEnergyAvailable": 9170.0, "internalTemp": 29.7, "ACGridCharging": 0.0}, {"timeStamp": "2024-08-30 10:06:38", "power": 1475.5, "batteryState": 3, "lifeTimeEnergyDischarged": 2657259, "lifeTimeEnergyCharged": 3273481, "batteryPercentageState": 40.0, "fullPackEnergyAvailable": 9170.0, "internalTemp": 29.8, "ACGridCharging": 0.0}, {"timeStamp": "2024-08-30 10:11:38", "power": 1598.5, "batteryState": 3, "lifeTimeEnergyDischarged": 2657259, "lifeTimeEnergyCharged": 3273622, "batteryPercentageState": 41.494003, "fullPackEnergyAvailable": 9170.0, "internalTemp": 30.0, "ACGridCharging": 0.0}, {"timeStamp": "2024-08-30 10:16:38", "power": 1643.88, "batteryState": 3, "lifeTimeEnergyDischarged": 2657259, "lifeTimeEnergyCharged": 3273772, "batteryPercentageState": 42.99891, "fullPackEnergyAvailable": 9170.0, "internalTemp": 30.2, "ACGridCharging": 0.0}, {"timeStamp": "2024-08-30 10:21:38", "power": 1679.94, "batteryState": 3, "lifeTimeEnergyDischarged": 2657259, "lifeTimeEnergyCharged": 3273925, "batteryPercentageState": 44.99455, "fullPackEnergyAvailable": 9170.0, "internalTemp": 30.4, "ACGridCharging": 0.0}, {"timeStamp": "2024-08-30 10:26:38", "power": 1739.25, "batteryState": 3, "lifeTimeEnergyDischarged": 2657259, "lifeTimeEnergyCharged": 3274084, "batteryPercentageState": 46.499454, "fullPackEnergyAvailable": 9170.0, "internalTemp": 30.6, "ACGridCharging": 0.0}, {"timeStamp": "2024-08-30 10:31:38", "power": 1802.56, "batteryState": 3, "lifeTimeEnergyDischarged": 2657259, "lifeTimeEnergyCharged": 3274247, "batteryPercentageState": 47.993458, "fullPackEnergyAvailable": 9170.0, "internalTemp": 30.8, "ACGridCharging": 0.0}, {"timeStamp": "2024-08-30 10:36:38", "power": 1798.06, "batteryState": 3, "lifeTimeEnergyDischarged": 2657259, "lifeTimeEnergyCharged": 3274412, "batteryPercentageState": 50.0, "fullPackEnergyAvailable": 9170.0, "internalTemp": 31.0, "ACGridCharging": 0.0}, {"timeStamp": "2024-08-30 10:41:38", "power": 1895.25, "batteryState": 3, "lifeTimeEnergyDischarged": 2657259, "lifeTimeEnergyCharged": 3274583, "batteryPercentageState": 51.494003, "fullPackEnergyAvailable": 9170.0, "internalTemp": 31.3, "ACGridCharging": 0.0}, {"timeStamp": "2024-08-30 10:46:38", "power": 1924.94, "batteryState": 3, "lifeTimeEnergyDischarged": 2657259, "lifeTimeEnergyCharged": 3274760, "batteryPercentageState": 53.48964, "fullPackEnergyAvailable": 9170.0, "internalTemp": 31.5, "ACGridCharging": 0.0}, {"timeStamp": "2024-08-30 10:51:38", "power": 1974.31, "batteryState": 3, "lifeTimeEnergyDischarged": 2657259, "lifeTimeEnergyCharged": 3274940, "batteryPercentageState": 55.49618, "fullPackEnergyAvailable": 9170.0, "internalTemp": 31.7, "ACGridCharging": 0.0}, {"timeStamp": "2024-08-30 10:56:38", "power": 2015.38, "batteryState": 3, "lifeTimeEnergyDischarged": 2657259, "lifeTimeEnergyCharged": 3275093, "batteryPercentageState": 56.990185, "fullPackEnergyAvailable": 9170.0, "internalTemp": 31.9, "ACGridCharging": 0.0}, {"timeStamp": "2024-08-30 11:01:38", "power": 2058.69, "batteryState": 3, "lifeTimeEnergyDischarged": 2657259, "lifeTimeEnergyCharged": 3275248, "batteryPercentageState": 58.495094, "fullPackEnergyAvailable": 9170.0, "internalTemp": 32.1, "ACGridCharging": 0.0}, {"timeStamp": "2024-08-30 11:06:38", "power": 2022.12, "batteryState": 3, "lifeTimeEnergyDischarged": 2657259, "lifeTimeEnergyCharged": 3275434, "batteryPercentageState": 60.49073, "fullPackEnergyAvailable": 9170.0, "internalTemp": 32.4, "ACGridCharging": 0.0}, {"timeStamp": "2024-08-30 11:11:38", "power": 2124.06, "batteryState": 3, "lifeTimeEnergyDischarged": 2657259, "lifeTimeEnergyCharged": 3275626, "batteryPercentageState": 62.497272, "fullPackEnergyAvailable": 9170.0, "internalTemp": 32.6, "ACGridCharging": 0.0}, {"timeStamp": "2024-08-30 11:16:38", "power": 2177.0, "batteryState": 3, "lifeTimeEnergyDischarged": 2657259, "lifeTimeEnergyCharged": 3275825, "batteryPercentageState": 64.49291, "fullPackEnergyAvailable": 9170.0, "internalTemp": 32.8, "ACGridCharging": 0.0}, {"timeStamp": "2024-08-30 11:21:38", "power": 2210.88, "batteryState": 3, "lifeTimeEnergyDischarged": 2657259, "lifeTimeEnergyCharged": 3276028, "batteryPercentageState": 66.49946, "fullPackEnergyAvailable": 9170.0, "internalTemp": 33.0, "ACGridCharging": 0.0}, {"timeStamp": "2024-08-30 11:26:38", "power": 2233.69, "batteryState": 3, "lifeTimeEnergyDischarged": 2657259, "lifeTimeEnergyCharged": 3276234, "batteryPercentageState": 68.495094, "fullPackEnergyAvailable": 9170.0, "internalTemp": 33.2, "ACGridCharging": 0.0}, {"timeStamp": "2024-08-30 11:31:38", "power": 2265.12, "batteryState": 3, "lifeTimeEnergyDischarged": 2657259, "lifeTimeEnergyCharged": 3276441, "batteryPercentageState": 70.49073, "fullPackEnergyAvailable": 9170.0, "internalTemp": 33.3, "ACGridCharging": 0.0}, {"timeStamp": "2024-08-30 11:36:38", "power": 2230.88, "batteryState": 3, "lifeTimeEnergyDischarged": 2657259, "lifeTimeEnergyCharged": 3276648, "batteryPercentageState": 72.49728, "fullPackEnergyAvailable": 9170.0, "internalTemp": 33.3, "ACGridCharging": 0.0}, {"timeStamp": "2024-08-30 11:41:38", "power": 2324.38, "batteryState": 3, "lifeTimeEnergyDischarged": 2657259, "lifeTimeEnergyCharged": 3276857, "batteryPercentageState": 74.49291, "fullPackEnergyAvailable": 9170.0, "internalTemp": 33.3, "ACGridCharging": 0.0}, {"timeStamp": "2024-08-30 11:46:38", "power": 1903.56, "batteryState": 3, "lifeTimeEnergyDischarged": 2657259, "lifeTimeEnergyCharged": 3277040, "batteryPercentageState": 76.49946, "fullPackEnergyAvailable": 9170.0, "internalTemp": 33.3, "ACGridCharging": 0.0}, {"timeStamp": "2024-08-30 11:51:38", "power": 1834.94, "batteryState": 3, "lifeTimeEnergyDischarged": 2657259, "lifeTimeEnergyCharged": 3277222, "batteryPercentageState": 77.993454, "fullPackEnergyAvailable": 9170.0, "internalTemp": 33.3, "ACGridCharging": 0.0}, {"timeStamp": "2024-08-30 11:56:38", "power": 1276.5, "batteryState": 3, "lifeTimeEnergyDischarged": 2657259, "lifeTimeEnergyCharged": 3277363, "batteryPercentageState": 79.49837, "fullPackEnergyAvailable": 9170.0, "internalTemp": 33.3, "ACGridCharging": 0.0}, {"timeStamp": "2024-08-30 12:01:38", "power": 1981.81, "batteryState": 3, "lifeTimeEnergyDischarged": 2657259, "lifeTimeEnergyCharged": 3277531, "batteryPercentageState": 80.99236, "fullPackEnergyAvailable": 9170.0, "internalTemp": 33.4, "ACGridCharging": 0.0}, {"timeStamp": "2024-08-30 12:06:38", "power": 2169.5, "batteryState": 3, "lifeTimeEnergyDischarged": 2657259, "lifeTimeEnergyCharged": 3277712, "batteryPercentageState": 82.99891, "fullPackEnergyAvailable": 9170.0, "internalTemp": 33.4, "ACGridCharging": 0.0}, {"timeStamp": "2024-08-30 12:11:38", "power": 2241.44, "batteryState": 3, "lifeTimeEnergyDischarged": 2657259, "lifeTimeEnergyCharged": 3277887, "batteryPercentageState": 84.49291, "fullPackEnergyAvailable": 9170.0, "internalTemp": 33.4, "ACGridCharging": 0.0}, {"timeStamp": "2024-08-30 12:16:38", "power": 2291.12, "batteryState": 3, "lifeTimeEnergyDischarged": 2657259, "lifeTimeEnergyCharged": 3278068, "batteryPercentageState": 86.49946, "fullPackEnergyAvailable": 9170.0, "internalTemp": 33.4, "ACGridCharging": 0.0}, {"timeStamp": "2024-08-30 12:21:38", "power": 2462.0, "batteryState": 3, "lifeTimeEnergyDischarged": 2657259, "lifeTimeEnergyCharged": 3278276, "batteryPercentageState": 88.495094, "fullPackEnergyAvailable": 9170.0, "internalTemp": 33.4, "ACGridCharging": 0.0}, {"timeStamp": "2024-08-30 12:26:38", "power": 2543.56, "batteryState": 3, "lifeTimeEnergyDischarged": 2657259, "lifeTimeEnergyCharged": 3278499, "batteryPercentageState": 90.49073, "fullPackEnergyAvailable": 9170.0, "internalTemp": 33.4, "ACGridCharging": 0.0}, {"timeStamp": "2024-08-30 12:31:38", "power": 2523.0, "batteryState": 3, "lifeTimeEnergyDischarged": 2657259, "lifeTimeEnergyCharged": 3278732, "batteryPercentageState": 92.49728, "fullPackEnergyAvailable": 9170.0, "internalTemp": 33.5, "ACGridCharging": 0.0}, {"timeStamp": "2024-08-30 12:36:38", "power": 2120.31, "batteryState": 3, "lifeTimeEnergyDischarged": 2657259, "lifeTimeEnergyCharged": 3278954, "batteryPercentageState": 94.49291, "fullPackEnergyAvailable": 9170.0, "internalTemp": 33.5, "ACGridCharging": 0.0}, {"timeStamp": "2024-08-30 12:41:38", "power": 2127.88, "batteryState": 3, "lifeTimeEnergyDischarged": 2657259, "lifeTimeEnergyCharged": 3279155, "batteryPercentageState": 96.49946, "fullPackEnergyAvailable": 9170.0, "internalTemp": 33.5, "ACGridCharging": 0.0}, {"timeStamp": "2024-08-30 12:46:38", "power": 1553.94, "batteryState": 3, "lifeTimeEnergyDischarged": 2657259, "lifeTimeEnergyCharged": 3279331, "batteryPercentageState": 97.993454, "fullPackEnergyAvailable": 9170.0, "internalTemp": 33.5, "ACGridCharging": 0.0}, {"timeStamp": "2024-08-30 12:51:38", "power": 1170.06, "batteryState": 3, "lifeTimeEnergyDischarged": 2657259, "lifeTimeEnergyCharged": 3279461, "batteryPercentageState": 98.99673, "fullPackEnergyAvailable": 9170.0, "internalTemp": 33.5, "ACGridCharging": 0.0}, {"timeStamp": "2024-08-30 12:56:38", "power": 0.0, "batteryState": 6, "lifeTimeEnergyDischarged": 2657259, "lifeTimeEnergyCharged": 3279533, "batteryPercentageState": 100.0, "fullPackEnergyAvailable": 9170.0, "internalTemp": 33.6, "ACGridCharging": 0.0}, {"timeStamp": "2024-08-30 13:01:38", "power": 0.0, "batteryState": 6, "lifeTimeEnergyDischarged": 2657259, "lifeTimeEnergyCharged": 3279533, "batteryPercentageState": 100.0, "fullPackEnergyAvailable": 9170.0, "internalTemp": 33.6, "ACGridCharging": 0.0}, {"timeStamp": "2024-08-30 13:06:38", "power": 0.0, "batteryState": 6, "lifeTimeEnergyDischarged": 2657259, "lifeTimeEnergyCharged": 3279533, "batteryPercentageState": 100.0, "fullPackEnergyAvailable": 9170.0, "internalTemp": 33.6, "ACGridCharging": 0.0}, {"timeStamp": "2024-08-30 13:11:38", "power": 0.0, "batteryState": 6, "lifeTimeEnergyDischarged": 2657259, "lifeTimeEnergyCharged": 3279533, "batteryPercentageState": 100.0, "fullPackEnergyAvailable": 9170.0, "internalTemp": 33.7, "ACGridCharging": 0.0}, {"timeStamp": "2024-08-30 13:16:38", "power": 0.0, "batteryState": 6, "lifeTimeEnergyDischarged": 2657259, "lifeTimeEnergyCharged": 3279533, "batteryPercentageState": 100.0, "fullPackEnergyAvailable": 9170.0, "internalTemp": 33.7, "ACGridCharging": 0.0}, {"timeStamp": "2024-08-30 13:21:38", "power": 0.0, "batteryState": 6, "lifeTimeEnergyDischarged": 2657259, "lifeTimeEnergyCharged": 3279533, "batteryPercentageState": 100.0, "fullPackEnergyAvailable": 9170.0, "internalTemp": 33.7, "ACGridCharging": 0.0}, {"timeStamp": "2024-08-30 13:26:38", "power": 0.0, "batteryState": 6, "lifeTimeEnergyDischarged": 2657259, "lifeTimeEnergyCharged": 3279533, "batteryPercentageState": 100.0, "fullPackEnergyAvailable": 9170.0, "internalTemp": 33.7, "ACGridCharging": 0.0}, {"timeStamp": "2024-08-30 13:31:38", "power": 0.0, "batteryState": 6, "lifeTimeEnergyDischarged": 2657259, "lifeTimeEnergyCharged": 3279533, "batteryPercentageState": 100.0, "fullPackEnergyAvailable": 9170.0, "internalTemp": 33.7, "ACGridCharging": 0.0}, {"timeStamp": "2024-08-30 13:36:38", "power": 0.0, "batteryState": 6, "lifeTimeEnergyDischarged": 2657259, "lifeTimeEnergyCharged": 3279533, "batteryPercentageState": 100.0, "fullPackEnergyAvailable": 9170.0, "internalTemp": 33.7, "ACGridCharging": 0.0}, {"timeStamp": "2024-08-30 13:41:38", "power": 0.0, "batteryState": 6, "lifeTimeEnergyDischarged": 2657259, "lifeTimeEnergyCharged": 3279533, "batteryPercentageState": 100.0, "fullPackEnergyAvailable": 9170.0, "internalTemp": 33.7, "ACGridCharging": 0.0}, {"timeStamp": "2024-08-30 13:46:38", "power": 0.0, "batteryState": 6, "lifeTimeEnergyDischarged": 2657259, "lifeTimeEnergyCharged": 3279533, "batteryPercentageState": 100.0, "fullPackEnergyAvailable": 9170.0, "internalTemp": 33.7, "ACGridCharging": 0.0}, {"timeStamp": "2024-08-30 13:51:38", "power": 1176.06, "batteryState": 3, "lifeTimeEnergyDischarged": 2657259, "lifeTimeEnergyCharged": 3279536, "batteryPercentageState": 98.99673, "fullPackEnergyAvailable": 9170.0, "internalTemp": 33.7, "ACGridCharging": 0.0}, {"timeStamp": "2024-08-30 13:56:38", "power": 0.0, "batteryState": 6, "lifeTimeEnergyDischarged": 2657259, "lifeTimeEnergyCharged": 3279592, "batteryPercentageState": 100.0, "fullPackEnergyAvailable": 9170.0, "internalTemp": 33.7, "ACGridCharging": 0.0}, {"timeStamp": "2024-08-30 14:01:38", "power": 0.0, "batteryState": 6, "lifeTimeEnergyDischarged": 2657259, "lifeTimeEnergyCharged": 3279592, "batteryPercentageState": 100.0, "fullPackEnergyAvailable": 9170.0, "internalTemp": 33.7, "ACGridCharging": 0.0}, {"timeStamp": "2024-08-30 14:06:38", "power": 0.0, "batteryState": 6, "lifeTimeEnergyDischarged": 2657259, "lifeTimeEnergyCharged": 3279592, "batteryPercentageState": 100.0, "fullPackEnergyAvailable": 9170.0, "internalTemp": 33.7, "ACGridCharging": 0.0}, {"timeStamp": "2024-08-30 14:11:38", "power": 0.0, "batteryState": 6, "lifeTimeEnergyDischarged": 2657259, "lifeTimeEnergyCharged": 3279592, "batteryPercentageState": 100.0, "fullPackEnergyAvailable": 9170.0, "internalTemp": 33.7, "ACGridCharging": 0.0}, {"timeStamp": "2024-08-30 14:16:38", "power": 0.0, "batteryState": 6, "lifeTimeEnergyDischarged": 2657259, "lifeTimeEnergyCharged": 3279592, "batteryPercentageState": 100.0, "fullPackEnergyAvailable": 9170.0, "internalTemp": 33.7, "ACGridCharging": 0.0}, {"timeStamp": "2024-08-30 14:21:38", "power": 0.0, "batteryState": 6, "lifeTimeEnergyDischarged": 2657259, "lifeTimeEnergyCharged": 3279592, "batteryPercentageState": 100.0, "fullPackEnergyAvailable": 9170.0, "internalTemp": 33.7, "ACGridCharging": 0.0}, {"timeStamp": "2024-08-30 14:26:38", "power": 0.0, "batteryState": 6, "lifeTimeEnergyDischarged": 2657259, "lifeTimeEnergyCharged": 3279592, "batteryPercentageState": 100.0, "fullPackEnergyAvailable": 9170.0, "internalTemp": 33.7, "ACGridCharging": 0.0}, {"timeStamp": "2024-08-30 14:31:38", "power": 0.0, "batteryState": 6, "lifeTimeEnergyDischarged": 2657259, "lifeTimeEnergyCharged": 3279592, "batteryPercentageState": 100.0, "fullPackEnergyAvailable": 9170.0, "internalTemp": 33.7, "ACGridCharging": 0.0}, {"timeStamp": "2024-08-30 14:36:38", "power": 0.0, "batteryState": 6, "lifeTimeEnergyDischarged": 2657259, "lifeTimeEnergyCharged": 3279592, "batteryPercentageState": 100.0, "fullPackEnergyAvailable": 9170.0, "internalTemp": 33.7, "ACGridCharging": 0.0}, {"timeStamp": "2024-08-30 14:41:38", "power": 0.0, "batteryState": 6, "lifeTimeEnergyDischarged": 2657259, "lifeTimeEnergyCharged": 3279592, "batteryPercentageState": 100.0, "fullPackEnergyAvailable": 9170.0, "internalTemp": 33.6, "ACGridCharging": 0.0}, {"timeStamp": "2024-08-30 14:46:38", "power": 0.0, "batteryState": 6, "lifeTimeEnergyDischarged": 2657259, "lifeTimeEnergyCharged": 3279592, "batteryPercentageState": 100.0, "fullPackEnergyAvailable": 9170.0, "internalTemp": 33.6, "ACGridCharging": 0.0}, {"timeStamp": "2024-08-30 14:51:38", "power": 0.0, "batteryState": 6, "lifeTimeEnergyDischarged": 2657259, "lifeTimeEnergyCharged": 3279592, "batteryPercentageState": 100.0, "fullPackEnergyAvailable": 9170.0, "internalTemp": 33.6, "ACGridCharging": 0.0}, {"timeStamp": "2024-08-30 14:56:38", "power": 0.0, "batteryState": 6, "lifeTimeEnergyDischarged": 2657259, "lifeTimeEnergyCharged": 3279592, "batteryPercentageState": 100.0, "fullPackEnergyAvailable": 9170.0, "internalTemp": 33.6, "ACGridCharging": 0.0}, {"timeStamp": "2024-08-30 15:01:38", "power": 0.0, "batteryState": 6, "lifeTimeEnergyDischarged": 2657259, "lifeTimeEnergyCharged": 3279592, "batteryPercentageState": 100.0, "fullPackEnergyAvailable": 9170.0, "internalTemp": 33.6, "ACGridCharging": 0.0}, {"timeStamp": "2024-08-30 15:06:38", "power": 0.0, "batteryState": 6, "lifeTimeEnergyDischarged": 2657259, "lifeTimeEnergyCharged": 3279592, "batteryPercentageState": 100.0, "fullPackEnergyAvailable": 9170.0, "internalTemp": 33.6, "ACGridCharging": 0.0}, {"timeStamp": "2024-08-30 15:11:38", "power": 0.0, "batteryState": 6, "lifeTimeEnergyDischarged": 2657259, "lifeTimeEnergyCharged": 3279592, "batteryPercentageState": 100.0, "fullPackEnergyAvailable": 9170.0, "internalTemp": 33.6, "ACGridCharging": 0.0}, {"timeStamp": "2024-08-30 15:16:38", "power": 0.0, "batteryState": 6, "lifeTimeEnergyDischarged": 2657259, "lifeTimeEnergyCharged": 3279592, "batteryPercentageState": 100.0, "fullPackEnergyAvailable": 9170.0, "internalTemp": 33.5, "ACGridCharging": 0.0}, {"timeStamp": "2024-08-30 15:21:38", "power": 0.0, "batteryState": 6, "lifeTimeEnergyDischarged": 2657259, "lifeTimeEnergyCharged": 3279592, "batteryPercentageState": 100.0, "fullPackEnergyAvailable": 9170.0, "internalTemp": 33.5, "ACGridCharging": 0.0}, {"timeStamp": "2024-08-30 15:26:38", "power": 0.0, "batteryState": 6, "lifeTimeEnergyDischarged": 2657259, "lifeTimeEnergyCharged": 3279592, "batteryPercentageState": 100.0, "fullPackEnergyAvailable": 9170.0, "internalTemp": 33.5, "ACGridCharging": 0.0}, {"timeStamp": "2024-08-30 15:31:38", "power": 0.0, "batteryState": 6, "lifeTimeEnergyDischarged": 2657259, "lifeTimeEnergyCharged": 3279592, "batteryPercentageState": 100.0, "fullPackEnergyAvailable": 9170.0, "internalTemp": 33.5, "ACGridCharging": 0.0}, {"timeStamp": "2024-08-30 15:36:38", "power": 0.0, "batteryState": 6, "lifeTimeEnergyDischarged": 2657259, "lifeTimeEnergyCharged": 3279592, "batteryPercentageState": 100.0, "fullPackEnergyAvailable": 9170.0, "internalTemp": 33.5, "ACGridCharging": 0.0}, {"timeStamp": "2024-08-30 15:41:38", "power": 0.0, "batteryState": 6, "lifeTimeEnergyDischarged": 2657259, "lifeTimeEnergyCharged": 3279592, "batteryPercentageState": 100.0, "fullPackEnergyAvailable": 9170.0, "internalTemp": 33.4, "ACGridCharging": 0.0}, {"timeStamp": "2024-08-30 15:46:38", "power": 0.0, "batteryState": 6, "lifeTimeEnergyDischarged": 2657259, "lifeTimeEnergyCharged": 3279592, "batteryPercentageState": 100.0, "fullPackEnergyAvailable": 9170.0, "internalTemp": 33.4, "ACGridCharging": 0.0}, {"timeStamp": "2024-08-30 15:51:38", "power": 0.0, "batteryState": 6, "lifeTimeEnergyDischarged": 2657259, "lifeTimeEnergyCharged": 3279592, "batteryPercentageState": 100.0, "fullPackEnergyAvailable": 9170.0, "internalTemp": 33.4, "ACGridCharging": 0.0}, {"timeStamp": "2024-08-30 15:56:38", "power": 1139.12, "batteryState": 3, "lifeTimeEnergyDischarged": 2657259, "lifeTimeEnergyCharged": 3279640, "batteryPercentageState": 99.49837, "fullPackEnergyAvailable": 9170.0, "internalTemp": 33.4, "ACGridCharging": 0.0}, {"timeStamp": "2024-08-30 16:01:38", "power": 0.0, "batteryState": 6, "lifeTimeEnergyDischarged": 2657259, "lifeTimeEnergyCharged": 3279655, "batteryPercentageState": 100.0, "fullPackEnergyAvailable": 9170.0, "internalTemp": 33.3, "ACGridCharging": 0.0}, {"timeStamp": "2024-08-30 16:06:38", "power": 0.0, "batteryState": 6, "lifeTimeEnergyDischarged": 2657259, "lifeTimeEnergyCharged": 3279655, "batteryPercentageState": 100.0, "fullPackEnergyAvailable": 9170.0, "internalTemp": 33.3, "ACGridCharging": 0.0}, {"timeStamp": "2024-08-30 16:11:38", "power": 0.0, "batteryState": 6, "lifeTimeEnergyDischarged": 2657259, "lifeTimeEnergyCharged": 3279655, "batteryPercentageState": 100.0, "fullPackEnergyAvailable": 9170.0, "internalTemp": 33.3, "ACGridCharging": 0.0}, {"timeStamp": "2024-08-30 16:16:38", "power": 0.0, "batteryState": 6, "lifeTimeEnergyDischarged": 2657259, "lifeTimeEnergyCharged": 3279655, "batteryPercentageState": 100.0, "fullPackEnergyAvailable": 9170.0, "internalTemp": 33.2, "ACGridCharging": 0.0}, {"timeStamp": "2024-08-30 16:21:38", "power": 0.0, "batteryState": 6, "lifeTimeEnergyDischarged": 2657259, "lifeTimeEnergyCharged": 3279655, "batteryPercentageState": 100.0, "fullPackEnergyAvailable": 9170.0, "internalTemp": 33.2, "ACGridCharging": 0.0}, {"timeStamp": "2024-08-30 16:26:38", "power": 0.0, "batteryState": 6, "lifeTimeEnergyDischarged": 2657259, "lifeTimeEnergyCharged": 3279655, "batteryPercentageState": 100.0, "fullPackEnergyAvailable": 9170.0, "internalTemp": 33.2, "ACGridCharging": 0.0}, {"timeStamp": "2024-08-30 16:31:38", "power": 0.0, "batteryState": 6, "lifeTimeEnergyDischarged": 2657259, "lifeTimeEnergyCharged": 3279655, "batteryPercentageState": 100.0, "fullPackEnergyAvailable": 9170.0, "internalTemp": 33.2, "ACGridCharging": 0.0}, {"timeStamp": "2024-08-30 16:36:38", "power": 0.0, "batteryState": 6, "lifeTimeEnergyDischarged": 2657259, "lifeTimeEnergyCharged": 3279655, "batteryPercentageState": 100.0, "fullPackEnergyAvailable": 9170.0, "internalTemp": 33.1, "ACGridCharging": 0.0}, {"timeStamp": "2024-08-30 16:41:38", "power": 0.0, "batteryState": 6, "lifeTimeEnergyDischarged": 2657259, "lifeTimeEnergyCharged": 3279655, "batteryPercentageState": 100.0, "fullPackEnergyAvailable": 9170.0, "internalTemp": 33.1, "ACGridCharging": 0.0}, {"timeStamp": "2024-08-30 16:46:38", "power": 0.0, "batteryState": 6, "lifeTimeEnergyDischarged": 2657259, "lifeTimeEnergyCharged": 3279655, "batteryPercentageState": 100.0, "fullPackEnergyAvailable": 9170.0, "internalTemp": 33.1, "ACGridCharging": 0.0}, {"timeStamp": "2024-08-30 16:51:38", "power": 0.0, "batteryState": 6, "lifeTimeEnergyDischarged": 2657259, "lifeTimeEnergyCharged": 3279655, "batteryPercentageState": 100.0, "fullPackEnergyAvailable": 9170.0, "internalTemp": 33.1, "ACGridCharging": 0.0}, {"timeStamp": "2024-08-30 16:56:38", "power": 0.0, "batteryState": 6, "lifeTimeEnergyDischarged": 2657259, "lifeTimeEnergyCharged": 3279655, "batteryPercentageState": 100.0, "fullPackEnergyAvailable": 9170.0, "internalTemp": 33.0, "ACGridCharging": 0.0}, {"timeStamp": "2024-08-30 17:01:38", "power": 0.0, "batteryState": 6, "lifeTimeEnergyDischarged": 2657259, "lifeTimeEnergyCharged": 3279655, "batteryPercentageState": 100.0, "fullPackEnergyAvailable": 9170.0, "internalTemp": 33.0, "ACGridCharging": 0.0}, {"timeStamp": "2024-08-30 17:06:38", "power": 0.0, "batteryState": 6, "lifeTimeEnergyDischarged": 2657259, "lifeTimeEnergyCharged": 3279655, "batteryPercentageState": 100.0, "fullPackEnergyAvailable": 9170.0, "internalTemp": 33.0, "ACGridCharging": 0.0}, {"timeStamp": "2024-08-30 17:11:38", "power": 0.0, "batteryState": 6, "lifeTimeEnergyDischarged": 2657259, "lifeTimeEnergyCharged": 3279655, "batteryPercentageState": 100.0, "fullPackEnergyAvailable": 9170.0, "internalTemp": 33.0, "ACGridCharging": 0.0}, {"timeStamp": "2024-08-30 17:16:38", "power": 0.0, "batteryState": 6, "lifeTimeEnergyDischarged": 2657259, "lifeTimeEnergyCharged": 3279655, "batteryPercentageState": 100.0, "fullPackEnergyAvailable": 9170.0, "internalTemp": 32.9, "ACGridCharging": 0.0}, {"timeStamp": "2024-08-30 17:21:38", "power": 0.0, "batteryState": 6, "lifeTimeEnergyDischarged": 2657259, "lifeTimeEnergyCharged": 3279655, "batteryPercentageState": 100.0, "fullPackEnergyAvailable": 9170.0, "internalTemp": 32.9, "ACGridCharging": 0.0}, {"timeStamp": "2024-08-30 17:26:38", "power": 0.0, "batteryState": 6, "lifeTimeEnergyDischarged": 2657259, "lifeTimeEnergyCharged": 3279655, "batteryPercentageState": 100.0, "fullPackEnergyAvailable": 9170.0, "internalTemp": 32.9, "ACGridCharging": 0.0}, {"timeStamp": "2024-08-30 17:31:38", "power": 0.0, "batteryState": 6, "lifeTimeEnergyDischarged": 2657259, "lifeTimeEnergyCharged": 3279655, "batteryPercentageState": 100.0, "fullPackEnergyAvailable": 9170.0, "internalTemp": 32.9, "ACGridCharging": 0.0}, {"timeStamp": "2024-08-30 17:36:38", "power": 0.0, "batteryState": 6, "lifeTimeEnergyDischarged": 2657259, "lifeTimeEnergyCharged": 3279655, "batteryPercentageState": 100.0, "fullPackEnergyAvailable": 9170.0, "internalTemp": 32.8, "ACGridCharging": 0.0}, {"timeStamp": "2024-08-30 17:41:38", "power": 0.0, "batteryState": 6, "lifeTimeEnergyDischarged": 2657259, "lifeTimeEnergyCharged": 3279655, "batteryPercentageState": 100.0, "fullPackEnergyAvailable": 9170.0, "internalTemp": 32.8, "ACGridCharging": 0.0}, {"timeStamp": "2024-08-30 17:46:38", "power": 0.0, "batteryState": 6, "lifeTimeEnergyDischarged": 2657259, "lifeTimeEnergyCharged": 3279655, "batteryPercentageState": 100.0, "fullPackEnergyAvailable": 9170.0, "internalTemp": 32.8, "ACGridCharging": 0.0}, {"timeStamp": "2024-08-30 17:51:38", "power": 0.0, "batteryState": 6, "lifeTimeEnergyDischarged": 2657259, "lifeTimeEnergyCharged": 3279655, "batteryPercentageState": 100.0, "fullPackEnergyAvailable": 9170.0, "internalTemp": 32.7, "ACGridCharging": 0.0}, {"timeStamp": "2024-08-30 17:56:38", "power": 0.0, "batteryState": 6, "lifeTimeEnergyDischarged": 2657259, "lifeTimeEnergyCharged": 3279655, "batteryPercentageState": 100.0, "fullPackEnergyAvailable": 9170.0, "internalTemp": 32.7, "ACGridCharging": 0.0}, {"timeStamp": "2024-08-30 18:01:38", "power": 0.0, "batteryState": 6, "lifeTimeEnergyDischarged": 2657259, "lifeTimeEnergyCharged": 3279655, "batteryPercentageState": 100.0, "fullPackEnergyAvailable": 9170.0, "internalTemp": 32.7, "ACGridCharging": 0.0}, {"timeStamp": "2024-08-30 18:06:38", "power": 0.0, "batteryState": 6, "lifeTimeEnergyDischarged": 2657259, "lifeTimeEnergyCharged": 3279655, "batteryPercentageState": 100.0, "fullPackEnergyAvailable": 9170.0, "internalTemp": 32.7, "ACGridCharging": 0.0}, {"timeStamp": "2024-08-30 18:11:38", "power": 0.0, "batteryState": 6, "lifeTimeEnergyDischarged": 2657259, "lifeTimeEnergyCharged": 3279655, "batteryPercentageState": 100.0, "fullPackEnergyAvailable": 9170.0, "internalTemp": 32.6, "ACGridCharging": 0.0}, {"timeStamp": "2024-08-30 18:16:38", "power": 0.0, "batteryState": 6, "lifeTimeEnergyDischarged": 2657259, "lifeTimeEnergyCharged": 3279655, "batteryPercentageState": 100.0, "fullPackEnergyAvailable": 9170.0, "internalTemp": 32.6, "ACGridCharging": 0.0}, {"timeStamp": "2024-08-30 18:21:38", "power": 0.0, "batteryState": 6, "lifeTimeEnergyDischarged": 2657259, "lifeTimeEnergyCharged": 3279655, "batteryPercentageState": 100.0, "fullPackEnergyAvailable": 9170.0, "internalTemp": 32.6, "ACGridCharging": 0.0}, {"timeStamp": "2024-08-30 18:26:38", "power": 0.0, "batteryState": 6, "lifeTimeEnergyDischarged": 2657259, "lifeTimeEnergyCharged": 3279655, "batteryPercentageState": 100.0, "fullPackEnergyAvailable": 9170.0, "internalTemp": 32.6, "ACGridCharging": 0.0}, {"timeStamp": "2024-08-30 18:31:38", "power": 0.0, "batteryState": 6, "lifeTimeEnergyDischarged": 2657259, "lifeTimeEnergyCharged": 3279655, "batteryPercentageState": 100.0, "fullPackEnergyAvailable": 9170.0, "internalTemp": 32.5, "ACGridCharging": 0.0}, {"timeStamp": "2024-08-30 18:36:38", "power": 0.0, "batteryState": 6, "lifeTimeEnergyDischarged": 2657259, "lifeTimeEnergyCharged": 3279655, "batteryPercentageState": 100.0, "fullPackEnergyAvailable": 9170.0, "internalTemp": 32.5, "ACGridCharging": 0.0}, {"timeStamp": "2024-08-30 18:41:38", "power": 0.0, "batteryState": 6, "lifeTimeEnergyDischarged": 2657259, "lifeTimeEnergyCharged": 3279655, "batteryPercentageState": 100.0, "fullPackEnergyAvailable": 9170.0, "internalTemp": 32.5, "ACGridCharging": 0.0}, {"timeStamp": "2024-08-30 18:46:38", "power": 0.0, "batteryState": 6, "lifeTimeEnergyDischarged": 2657259, "lifeTimeEnergyCharged": 3279655, "batteryPercentageState": 100.0, "fullPackEnergyAvailable": 9170.0, "internalTemp": 32.4, "ACGridCharging": 0.0}, {"timeStamp": "2024-08-30 18:51:38", "power": 0.0, "batteryState": 6, "lifeTimeEnergyDischarged": 2657259, "lifeTimeEnergyCharged": 3279655, "batteryPercentageState": 100.0, "fullPackEnergyAvailable": 9170.0, "internalTemp": 32.4, "ACGridCharging": 0.0}, {"timeStamp": "2024-08-30 18:56:38", "power": 0.0, "batteryState": 6, "lifeTimeEnergyDischarged": 2657260, "lifeTimeEnergyCharged": 3279655, "batteryPercentageState": 100.0, "fullPackEnergyAvailable": 9170.0, "internalTemp": 32.4, "ACGridCharging": 0.0}, {"timeStamp": "2024-08-30 19:01:38", "power": 5.8125, "batteryState": 6, "lifeTimeEnergyDischarged": 2657262, "lifeTimeEnergyCharged": 3279655, "batteryPercentageState": 100.0, "fullPackEnergyAvailable": 9170.0, "internalTemp": 32.3, "ACGridCharging": 0.0}, {"timeStamp": "2024-08-30 19:06:38", "power": 5.9375, "batteryState": 6, "lifeTimeEnergyDischarged": 2657269, "lifeTimeEnergyCharged": 3279655, "batteryPercentageState": 100.0, "fullPackEnergyAvailable": 9170.0, "internalTemp": 32.3, "ACGridCharging": 0.0}, {"timeStamp": "2024-08-30 19:11:38", "power": -93.0, "batteryState": 4, "lifeTimeEnergyDischarged": 2657277, "lifeTimeEnergyCharged": 3279655, "batteryPercentageState": 98.99673, "fullPackEnergyAvailable": 9170.0, "internalTemp": 32.3, "ACGridCharging": 0.0}, {"timeStamp": "2024-08-30 19:16:38", "power": -177.875, "batteryState": 4, "lifeTimeEnergyDischarged": 2657287, "lifeTimeEnergyCharged": 3279655, "batteryPercentageState": 98.99673, "fullPackEnergyAvailable": 9170.0, "internalTemp": 32.3, "ACGridCharging": 0.0}, {"timeStamp": "2024-08-30 19:21:38", "power": -120.875, "batteryState": 4, "lifeTimeEnergyDischarged": 2657302, "lifeTimeEnergyCharged": 3279655, "batteryPercentageState": 98.99673, "fullPackEnergyAvailable": 9170.0, "internalTemp": 32.3, "ACGridCharging": 0.0}, {"timeStamp": "2024-08-30 19:26:38", "power": -138.5, "batteryState": 4, "lifeTimeEnergyDischarged": 2657313, "lifeTimeEnergyCharged": 3279655, "batteryPercentageState": 98.99673, "fullPackEnergyAvailable": 9170.0, "internalTemp": 32.2, "ACGridCharging": 0.0}, {"timeStamp": "2024-08-30 19:31:38", "power": -164.312, "batteryState": 4, "lifeTimeEnergyDischarged": 2657322, "lifeTimeEnergyCharged": 3279655, "batteryPercentageState": 98.99673, "fullPackEnergyAvailable": 9170.0, "internalTemp": 32.2, "ACGridCharging": 0.0}, {"timeStamp": "2024-08-30 19:36:38", "power": -162.5, "batteryState": 4, "lifeTimeEnergyDischarged": 2657335, "lifeTimeEnergyCharged": 3279655, "batteryPercentageState": 98.495094, "fullPackEnergyAvailable": 9170.0, "internalTemp": 32.2, "ACGridCharging": 0.0}, {"timeStamp": "2024-08-30 19:41:38", "power": -229.375, "batteryState": 4, "lifeTimeEnergyDischarged": 2657351, "lifeTimeEnergyCharged": 3279655, "batteryPercentageState": 98.495094, "fullPackEnergyAvailable": 9170.0, "internalTemp": 32.2, "ACGridCharging": 0.0}, {"timeStamp": "2024-08-30 19:46:38", "power": -188.812, "batteryState": 4, "lifeTimeEnergyDischarged": 2657373, "lifeTimeEnergyCharged": 3279655, "batteryPercentageState": 98.495094, "fullPackEnergyAvailable": 9170.0, "internalTemp": 32.1, "ACGridCharging": 0.0}, {"timeStamp": "2024-08-30 19:51:38", "power": -193.0, "batteryState": 4, "lifeTimeEnergyDischarged": 2657389, "lifeTimeEnergyCharged": 3279655, "batteryPercentageState": 97.993454, "fullPackEnergyAvailable": 9170.0, "internalTemp": 32.1, "ACGridCharging": 0.0}, {"timeStamp": "2024-08-30 19:56:38", "power": -170.0, "batteryState": 4, "lifeTimeEnergyDischarged": 2657407, "lifeTimeEnergyCharged": 3279655, "batteryPercentageState": 97.993454, "fullPackEnergyAvailable": 9170.0, "internalTemp": 32.1, "ACGridCharging": 0.0}, {"timeStamp": "2024-08-30 20:01:38", "power": -172.562, "batteryState": 4, "lifeTimeEnergyDischarged": 2657423, "lifeTimeEnergyCharged": 3279655, "batteryPercentageState": 97.993454, "fullPackEnergyAvailable": 9170.0, "internalTemp": 32.1, "ACGridCharging": 0.0}, {"timeStamp": "2024-08-30 20:06:38", "power": -161.188, "batteryState": 4, "lifeTimeEnergyDischarged": 2657439, "lifeTimeEnergyCharged": 3279655, "batteryPercentageState": 97.49182, "fullPackEnergyAvailable": 9170.0, "internalTemp": 32.1, "ACGridCharging": 0.0}, {"timeStamp": "2024-08-30 20:11:38", "power": -256.875, "batteryState": 4, "lifeTimeEnergyDischarged": 2657461, "lifeTimeEnergyCharged": 3279655, "batteryPercentageState": 97.49182, "fullPackEnergyAvailable": 9170.0, "internalTemp": 32.1, "ACGridCharging": 0.0}, {"timeStamp": "2024-08-30 20:16:38", "power": -188.688, "batteryState": 4, "lifeTimeEnergyDischarged": 2657476, "lifeTimeEnergyCharged": 3279655, "batteryPercentageState": 97.49182, "fullPackEnergyAvailable": 9170.0, "internalTemp": 32.1, "ACGridCharging": 0.0}, {"timeStamp": "2024-08-30 20:21:38", "power": -146.5, "batteryState": 4, "lifeTimeEnergyDischarged": 2657492, "lifeTimeEnergyCharged": 3279655, "batteryPercentageState": 96.99019, "fullPackEnergyAvailable": 9170.0, "internalTemp": 32.0, "ACGridCharging": 0.0}, {"timeStamp": "2024-08-30 20:26:38", "power": -167.25, "batteryState": 4, "lifeTimeEnergyDischarged": 2657507, "lifeTimeEnergyCharged": 3279655, "batteryPercentageState": 96.99019, "fullPackEnergyAvailable": 9170.0, "internalTemp": 32.0, "ACGridCharging": 0.0}, {"timeStamp": "2024-08-30 20:31:38", "power": -104.937, "batteryState": 4, "lifeTimeEnergyDischarged": 2657522, "lifeTimeEnergyCharged": 3279655, "batteryPercentageState": 96.49946, "fullPackEnergyAvailable": 9170.0, "internalTemp": 32.0, "ACGridCharging": 0.0}, {"timeStamp": "2024-08-30 20:36:38", "power": -165.25, "batteryState": 4, "lifeTimeEnergyDischarged": 2657536, "lifeTimeEnergyCharged": 3279655, "batteryPercentageState": 96.49946, "fullPackEnergyAvailable": 9170.0, "internalTemp": 32.0, "ACGridCharging": 0.0}, {"timeStamp": "2024-08-30 20:41:38", "power": -205.0, "batteryState": 4, "lifeTimeEnergyDischarged": 2657554, "lifeTimeEnergyCharged": 3279655, "batteryPercentageState": 96.49946, "fullPackEnergyAvailable": 9170.0, "internalTemp": 32.0, "ACGridCharging": 0.0}, {"timeStamp": "2024-08-30 20:46:38", "power": -205.875, "batteryState": 4, "lifeTimeEnergyDischarged": 2657573, "lifeTimeEnergyCharged": 3279655, "batteryPercentageState": 95.99782, "fullPackEnergyAvailable": 9170.0, "internalTemp": 32.0, "ACGridCharging": 0.0}, {"timeStamp": "2024-08-30 20:51:38", "power": -206.125, "batteryState": 4, "lifeTimeEnergyDischarged": 2657591, "lifeTimeEnergyCharged": 3279655, "batteryPercentageState": 95.99782, "fullPackEnergyAvailable": 9170.0, "internalTemp": 32.0, "ACGridCharging": 0.0}, {"timeStamp": "2024-08-30 20:56:38", "power": -176.75, "batteryState": 4, "lifeTimeEnergyDischarged": 2657612, "lifeTimeEnergyCharged": 3279655, "batteryPercentageState": 95.99782, "fullPackEnergyAvailable": 9170.0, "internalTemp": 31.9, "ACGridCharging": 0.0}, {"timeStamp": "2024-08-30 21:01:38", "power": -284.0, "batteryState": 4, "lifeTimeEnergyDischarged": 2657634, "lifeTimeEnergyCharged": 3279655, "batteryPercentageState": 95.496185, "fullPackEnergyAvailable": 9170.0, "internalTemp": 31.9, "ACGridCharging": 0.0}, {"timeStamp": "2024-08-30 21:06:38", "power": -150.688, "batteryState": 4, "lifeTimeEnergyDischarged": 2657654, "lifeTimeEnergyCharged": 3279655, "batteryPercentageState": 95.496185, "fullPackEnergyAvailable": 9170.0, "internalTemp": 31.9, "ACGridCharging": 0.0}, {"timeStamp": "2024-08-30 21:11:38", "power": -206.688, "batteryState": 4, "lifeTimeEnergyDischarged": 2657673, "lifeTimeEnergyCharged": 3279655, "batteryPercentageState": 95.496185, "fullPackEnergyAvailable": 9170.0, "internalTemp": 31.9, "ACGridCharging": 0.0}, {"timeStamp": "2024-08-30 21:16:38", "power": -233.562, "batteryState": 4, "lifeTimeEnergyDischarged": 2657690, "lifeTimeEnergyCharged": 3279655, "batteryPercentageState": 94.994545, "fullPackEnergyAvailable": 9170.0, "internalTemp": 31.9, "ACGridCharging": 0.0}, {"timeStamp": "2024-08-30 21:21:38", "power": -173.812, "batteryState": 4, "lifeTimeEnergyDischarged": 2657708, "lifeTimeEnergyCharged": 3279655, "batteryPercentageState": 94.994545, "fullPackEnergyAvailable": 9170.0, "internalTemp": 31.9, "ACGridCharging": 0.0}, {"timeStamp": "2024-08-30 21:26:38", "power": -218.188, "batteryState": 4, "lifeTimeEnergyDischarged": 2657728, "lifeTimeEnergyCharged": 3279655, "batteryPercentageState": 94.49291, "fullPackEnergyAvailable": 9170.0, "internalTemp": 31.9, "ACGridCharging": 0.0}, {"timeStamp": "2024-08-30 21:31:38", "power": -151.0, "batteryState": 4, "lifeTimeEnergyDischarged": 2657744, "lifeTimeEnergyCharged": 3279655, "batteryPercentageState": 94.49291, "fullPackEnergyAvailable": 9170.0, "internalTemp": 31.8, "ACGridCharging": 0.0}, {"timeStamp": "2024-08-30 21:36:38", "power": -148.875, "batteryState": 4, "lifeTimeEnergyDischarged": 2657758, "lifeTimeEnergyCharged": 3279655, "batteryPercentageState": 94.49291, "fullPackEnergyAvailable": 9170.0, "internalTemp": 31.8, "ACGridCharging": 0.0}, {"timeStamp": "2024-08-30 21:41:38", "power": -115.375, "batteryState": 4, "lifeTimeEnergyDischarged": 2657770, "lifeTimeEnergyCharged": 3279655, "batteryPercentageState": 93.99128, "fullPackEnergyAvailable": 9170.0, "internalTemp": 31.8, "ACGridCharging": 0.0}, {"timeStamp": "2024-08-30 21:46:38", "power": -187.875, "batteryState": 4, "lifeTimeEnergyDischarged": 2657785, "lifeTimeEnergyCharged": 3279655, "batteryPercentageState": 93.99128, "fullPackEnergyAvailable": 9170.0, "internalTemp": 31.8, "ACGridCharging": 0.0}, {"timeStamp": "2024-08-30 21:51:38", "power": -205.563, "batteryState": 4, "lifeTimeEnergyDischarged": 2657804, "lifeTimeEnergyCharged": 3279655, "batteryPercentageState": 93.48964, "fullPackEnergyAvailable": 9170.0, "internalTemp": 31.8, "ACGridCharging": 0.0}, {"timeStamp": "2024-08-30 21:56:38", "power": -144.312, "batteryState": 4, "lifeTimeEnergyDischarged": 2657824, "lifeTimeEnergyCharged": 3279655, "batteryPercentageState": 93.48964, "fullPackEnergyAvailable": 9170.0, "internalTemp": 31.8, "ACGridCharging": 0.0}, {"timeStamp": "2024-08-30 22:01:38", "power": -144.25, "batteryState": 4, "lifeTimeEnergyDischarged": 2657840, "lifeTimeEnergyCharged": 3279655, "batteryPercentageState": 93.48964, "fullPackEnergyAvailable": 9170.0, "internalTemp": 31.8, "ACGridCharging": 0.0}, {"timeStamp": "2024-08-30 22:03:36", "power": -148.312, "batteryState": 4, "lifeTimeEnergyDischarged": 2657846, "lifeTimeEnergyCharged": 3279655, "batteryPercentageState": 92.99891, "fullPackEnergyAvailable": 9170.0, "internalTemp": 31.7, "ACGridCharging": 0.0}, {"timeStamp": "2024-08-30 22:06:39", "power": -165.0, "batteryState": 4, "lifeTimeEnergyDischarged": 2657850, "lifeTimeEnergyCharged": 3279655, "batteryPercentageState": 92.99891, "fullPackEnergyAvailable": 9170.0, "internalTemp": 31.7, "ACGridCharging": 0.0}, {"timeStamp": "2024-08-30 22:11:39", "power": -181.875, "batteryState": 4, "lifeTimeEnergyDischarged": 2657866, "lifeTimeEnergyCharged": 3279655, "batteryPercentageState": 92.99891, "fullPackEnergyAvailable": 9170.0, "internalTemp": 31.7, "ACGridCharging": 0.0}, {"timeStamp": "2024-08-30 22:16:39", "power": -238.062, "batteryState": 4, "lifeTimeEnergyDischarged": 2657886, "lifeTimeEnergyCharged": 3279655, "batteryPercentageState": 92.49728, "fullPackEnergyAvailable": 9170.0, "internalTemp": 31.7, "ACGridCharging": 0.0}, {"timeStamp": "2024-08-30 22:21:39", "power": -161.062, "batteryState": 4, "lifeTimeEnergyDischarged": 2657906, "lifeTimeEnergyCharged": 3279655, "batteryPercentageState": 92.49728, "fullPackEnergyAvailable": 9170.0, "internalTemp": 31.7, "ACGridCharging": 0.0}, {"timeStamp": "2024-08-30 22:26:39", "power": -188.938, "batteryState": 4, "lifeTimeEnergyDischarged": 2657923, "lifeTimeEnergyCharged": 3279655, "batteryPercentageState": 92.49728, "fullPackEnergyAvailable": 9170.0, "internalTemp": 31.7, "ACGridCharging": 0.0}, {"timeStamp": "2024-08-30 22:31:39", "power": -206.562, "batteryState": 4, "lifeTimeEnergyDischarged": 2657940, "lifeTimeEnergyCharged": 3279655, "batteryPercentageState": 91.995636, "fullPackEnergyAvailable": 9170.0, "internalTemp": 31.6, "ACGridCharging": 0.0}, {"timeStamp": "2024-08-30 22:36:39", "power": -197.75, "batteryState": 4, "lifeTimeEnergyDischarged": 2657960, "lifeTimeEnergyCharged": 3279655, "batteryPercentageState": 91.995636, "fullPackEnergyAvailable": 9170.0, "internalTemp": 31.6, "ACGridCharging": 0.0}, {"timeStamp": "2024-08-30 22:41:39", "power": -177.75, "batteryState": 4, "lifeTimeEnergyDischarged": 2657979, "lifeTimeEnergyCharged": 3279655, "batteryPercentageState": 91.995636, "fullPackEnergyAvailable": 9170.0, "internalTemp": 31.6, "ACGridCharging": 0.0}, {"timeStamp": "2024-08-30 22:46:39", "power": -179.125, "batteryState": 4, "lifeTimeEnergyDischarged": 2657997, "lifeTimeEnergyCharged": 3279655, "batteryPercentageState": 91.494, "fullPackEnergyAvailable": 9170.0, "internalTemp": 31.6, "ACGridCharging": 0.0}, {"timeStamp": "2024-08-30 22:51:39", "power": -202.0, "batteryState": 4, "lifeTimeEnergyDischarged": 2658015, "lifeTimeEnergyCharged": 3279655, "batteryPercentageState": 90.49073, "fullPackEnergyAvailable": 9170.0, "internalTemp": 31.6, "ACGridCharging": 0.0}, {"timeStamp": "2024-08-30 22:56:39", "power": -184.875, "batteryState": 4, "lifeTimeEnergyDischarged": 2658035, "lifeTimeEnergyCharged": 3279655, "batteryPercentageState": 90.49073, "fullPackEnergyAvailable": 9170.0, "internalTemp": 31.6, "ACGridCharging": 0.0}, {"timeStamp": "2024-08-30 23:01:39", "power": -163.375, "batteryState": 4, "lifeTimeEnergyDischarged": 2658054, "lifeTimeEnergyCharged": 3279655, "batteryPercentageState": 90.49073, "fullPackEnergyAvailable": 9170.0, "internalTemp": 31.6, "ACGridCharging": 0.0}, {"timeStamp": "2024-08-30 23:06:39", "power": -156.438, "batteryState": 4, "lifeTimeEnergyDischarged": 2658073, "lifeTimeEnergyCharged": 3279655, "batteryPercentageState": 90.0, "fullPackEnergyAvailable": 9170.0, "internalTemp": 31.5, "ACGridCharging": 0.0}, {"timeStamp": "2024-08-30 23:11:39", "power": -382.188, "batteryState": 4, "lifeTimeEnergyDischarged": 2658101, "lifeTimeEnergyCharged": 3279655, "batteryPercentageState": 90.0, "fullPackEnergyAvailable": 9170.0, "internalTemp": 31.5, "ACGridCharging": 0.0}, {"timeStamp": "2024-08-30 23:16:39", "power": -162.562, "batteryState": 4, "lifeTimeEnergyDischarged": 2658118, "lifeTimeEnergyCharged": 3279655, "batteryPercentageState": 90.0, "fullPackEnergyAvailable": 9170.0, "internalTemp": 31.5, "ACGridCharging": 0.0}, {"timeStamp": "2024-08-30 23:21:39", "power": -191.438, "batteryState": 4, "lifeTimeEnergyDischarged": 2658134, "lifeTimeEnergyCharged": 3279655, "batteryPercentageState": 89.49837, "fullPackEnergyAvailable": 9170.0, "internalTemp": 31.5, "ACGridCharging": 0.0}, {"timeStamp": "2024-08-30 23:26:39", "power": -264.938, "batteryState": 4, "lifeTimeEnergyDischarged": 2658152, "lifeTimeEnergyCharged": 3279655, "batteryPercentageState": 89.49837, "fullPackEnergyAvailable": 9170.0, "internalTemp": 31.5, "ACGridCharging": 0.0}, {"timeStamp": "2024-08-30 23:31:39", "power": -145.188, "batteryState": 4, "lifeTimeEnergyDischarged": 2658172, "lifeTimeEnergyCharged": 3279655, "batteryPercentageState": 89.49837, "fullPackEnergyAvailable": 9170.0, "internalTemp": 31.5, "ACGridCharging": 0.0}, {"timeStamp": "2024-08-30 23:36:39", "power": -186.438, "batteryState": 4, "lifeTimeEnergyDischarged": 2658188, "lifeTimeEnergyCharged": 3279655, "batteryPercentageState": 88.99673, "fullPackEnergyAvailable": 9170.0, "internalTemp": 31.5, "ACGridCharging": 0.0}, {"timeStamp": "2024-08-30 23:41:39", "power": -208.562, "batteryState": 4, "lifeTimeEnergyDischarged": 2658207, "lifeTimeEnergyCharged": 3279655, "batteryPercentageState": 88.99673, "fullPackEnergyAvailable": 9170.0, "internalTemp": 31.5, "ACGridCharging": 0.0}, {"timeStamp": "2024-08-30 23:46:39", "power": -203.812, "batteryState": 4, "lifeTimeEnergyDischarged": 2658227, "lifeTimeEnergyCharged": 3279655, "batteryPercentageState": 88.99673, "fullPackEnergyAvailable": 9170.0, "internalTemp": 31.4, "ACGridCharging": 0.0}, {"timeStamp": "2024-08-30 23:51:39", "power": -234.438, "batteryState": 4, "lifeTimeEnergyDischarged": 2658247, "lifeTimeEnergyCharged": 3279655, "batteryPercentageState": 88.495094, "fullPackEnergyAvailable": 9170.0, "internalTemp": 31.4, "ACGridCharging": 0.0}, {"timeStamp": "2024-08-30 23:56:39", "power": -265.438, "batteryState": 4, "lifeTimeEnergyDischarged": 2658275, "lifeTimeEnergyCharged": 3279655, "batteryPercentageState": 88.495094, "fullPackEnergyAvailable": 9170.0, "internalTemp": 31.4, "ACGridCharging": 0.0}]}]}}